[{"Id": 1743, "ParentId": 1510, "Level": 3, "Number": 1, "EnglishIndexName": "7th Night Namaz", "GujaratiIndexName": null, "RUrduIndexName": "7th Shab ki Namaz", "UrduIndexName": "۷؍شب کی نماز", "EnglishName": "7th Night Namaz", "GujaratiName": null, "RUrduName": "7th Shab ki Namaz", "UrduName": "۷؍شب کی نماز", "HyperlinkEnglishName": "7th Eve Namaz of Ramazan", "HyperlinkGujaratiName": null, "HyperlinkRUrduName": "7th Shab-e-Ramazan ki Namaz", "HyperlinkUrduName": "۷؍شب رمضان کی نماز", "IsVisible": 1, "HasChildren": 0, "IsNavigableMap": 0, "CategoryId": 5, "AudioIndexId": 0}, {"Id": 1744, "ParentId": 1510, "Level": 3, "Number": 2, "EnglishIndexName": "7th Night Dua", "GujaratiIndexName": null, "RUrduIndexName": "7th Shab ki Dua", "UrduIndexName": "۷؍شب کی دُعا", "EnglishName": "7th Night Dua", "GujaratiName": null, "RUrduName": "7th Shab ki Dua", "UrduName": "۷؍شب کی دُعا", "HyperlinkEnglishName": "7th Night Dua", "HyperlinkGujaratiName": null, "HyperlinkRUrduName": "7th Shab ki Dua", "HyperlinkUrduName": "۷؍شب کی دُعا", "IsVisible": 1, "HasChildren": 0, "IsNavigableMap": 0, "CategoryId": 5, "AudioIndexId": 0}, {"Id": 1745, "ParentId": 1510, "Level": 3, "Number": 3, "EnglishIndexName": "7th Day Dua", "GujaratiIndexName": null, "RUrduIndexName": "7th Din ki Dua", "UrduIndexName": "۷؍دن کی دُعا", "EnglishName": "7th Day Dua", "GujaratiName": null, "RUrduName": "7th Din ki Dua", "UrduName": "۷؍دن کی دُعا", "HyperlinkEnglishName": "7th Day Dua", "HyperlinkGujaratiName": null, "HyperlinkRUrduName": "7th Din ki Dua", "HyperlinkUrduName": "۷؍دن کی دُعا", "IsVisible": 1, "HasChildren": 0, "IsNavigableMap": 0, "CategoryId": 5, "AudioIndexId": 0}]